LICENSE
MANIFEST.in
README.md
setup.cfg
setup.py
django_mp_shop_wishlist.egg-info/PKG-INFO
django_mp_shop_wishlist.egg-info/SOURCES.txt
django_mp_shop_wishlist.egg-info/dependency_links.txt
django_mp_shop_wishlist.egg-info/top_level.txt
wishlist/__init__.py
wishlist/exceptions.py
wishlist/middleware.py
wishlist/models.py
wishlist/urls.py
wishlist/views.py
wishlist/locale/en/LC_MESSAGES/django.mo
wishlist/locale/en/LC_MESSAGES/django.po
wishlist/locale/ru/LC_MESSAGES/django.mo
wishlist/locale/ru/LC_MESSAGES/django.po
wishlist/locale/uk/LC_MESSAGES/django.mo
wishlist/locale/uk/LC_MESSAGES/django.po
wishlist/migrations/0001_initial.py
wishlist/migrations/__init__.py
wishlist/templatetags/__init__.py
wishlist/templatetags/wishlist.py