Metadata-Version: 2.1
Name: django-mp-shop-wishlist
Version: 2.0
Summary: Django shop wishlist apps
Home-page: https://github.com/pmaigutyak/mp-shop-wishlist
Author: Paul Maigutyak
Author-email: pmaigutyak@gmail.com
License: MIT
Download-URL: https://github.com/pmaigutyak/mp-shop-wishlist/archive/2.0.tar.gz
Platform: UNKNOWN
License-File: LICENSE
